microscopemetrics/__init__.py
microscopemetrics/_version.py
microscopemetrics/analyses/__init__.py
microscopemetrics/analyses/argolight.py
microscopemetrics/analyses/field_illumination.py
microscopemetrics/analyses/mappings.py
microscopemetrics/analyses/psf_beads.py
microscopemetrics/analyses/tools.py
microscopemetrics/analyses/user_experiment.py
microscopemetrics/data_schema/samples/test.py
microscopemetrics/data_schema/samples/test.yaml
microscopemetrics/devices/__init__.py
microscopemetrics/devices/devices.py
microscopemetrics/strategies/__init__.py
microscopemetrics/strategies/field_illumination.py
microscopemetrics/strategies/psf_beads.py
microscopemetrics/strategies/user_experiment.py
microscopemetrics-0.2.3.dist-info/LICENSE
microscopemetrics-0.2.3.dist-info/METADATA
microscopemetrics-0.2.3.dist-info/WHEEL
microscopemetrics-0.2.3.dist-info/RECORD
