Metadata-Version: 2.3
Name: microscopemetrics
Version: 0.2.3
Summary: A package providing analysis routines to measure the performance of microscopes used in biomedical research
License: GPL-3.0-only
Keywords: microscopy,metrology
Author: Julio Mateos Langerak
Author-email: julio.mateos-langerak@igh,cnrs.fr
Maintainer: Julio Mateos Langerak
Maintainer-email: julio.mateos-langerak@igh,cnrs.fr
Requires-Python: >=3.9.18,<3.12
Classifier: Development Status :: 4 - Beta
Classifier: Intended Audience :: Science/Research
Classifier: License :: OSI Approved :: GNU General Public License v3 (GPLv3)
Classifier: Programming Language :: Python :: 3
Classifier: Programming Language :: Python :: 3.10
Classifier: Programming Language :: Python :: 3.11
Classifier: Programming Language :: Python :: 3.12
Classifier: Programming Language :: Python :: 3.9
Classifier: Programming Language :: Python :: Implementation :: CPython
Classifier: Topic :: Scientific/Engineering :: Image Processing
Requires-Dist: microscopemetrics-schema (==0.0.4)
Requires-Dist: numpy (>=2,<3)
Requires-Dist: pandas (>=2,<3)
Requires-Dist: scikit-image (>=0,<1)
Requires-Dist: scipy (>=1,<2)
Project-URL: Documentation, https://github.com/MontpellierRessourcesImagerie/microscope-metrics/tree/master/docs
Project-URL: Homepage, https://github.com/MontpellierRessourcesImagerie/microscope-metrics
Project-URL: Repository, https://github.com/MontpellierRessourcesImagerie/microscope-metrics
